{
	"id": "30e755f7-452c-4ea6-bd3d-15f4d090c0e7",
	"name": "store-test.environment",
	"values": [
		{
			"key": "testedProductID",
			"value": "",
			"type": "default",
			"enabled": true
		},
		{
			"key": "testedOrderID",
			"value": "",
			"type": "default",
			"enabled": true
		},
		{
			"key": "testedUserID",
			"value": "",
			"type": "default",
			"enabled": true
		}
	],
	"_postman_variable_scope": "environment",
	"_postman_exported_at": "2022-10-14T15:10:39.093Z",
	"_postman_exported_using": "Postman/10.0.27"
}